suid_interpreter/3D/__init__.py
suid_interpreter/3D/cube.py
suid_interpreter/3D/main.py
suid_interpreter/3D/point.py
suid_interpreter/3D/radioButton.py
suid_interpreter/3D/slider.py
suid_interpreter/__init__.py
suid_interpreter/cartesian.py
suid_interpreter/interpreter-OLD.jpg
suid_interpreter/interpreter_ar-OLD.jpg
suid_interpreter/plot.py
suid_interpreter/server.py
suid_interpreter/worldmapping.py
suid_interpreter-0.1.2.dist-info/METADATA
suid_interpreter-0.1.2.dist-info/WHEEL
suid_interpreter-0.1.2.dist-info/RECORD
